ppong/__init__.py
ppong/get00_annotations.py
ppong/get01_spectrograms.py
ppong/get02_peaks.py
ppong/get03_stats.py
ppong/plots.py
ppong/run.py
ppong-0.0.2.dist-info/LICENSE
ppong-0.0.2.dist-info/METADATA
ppong-0.0.2.dist-info/WHEEL
ppong-0.0.2.dist-info/entry_points.txt
ppong-0.0.2.dist-info/top_level.txt
ppong-0.0.2.dist-info/RECORD
